[
  {
    "id": "relux-86797733e6",
    "provider": "relux",
    "provider_label": "Relux",
    "site_targets": [
      "welltrip"
    ],
    "article_slug": "",
    "title": "→Relux × au ID連携キャンペーン",
    "category": "567_relux-discount-campaigns",
    "discount": "抽選で最大10,000 / Pontaポイント付与",
    "stock_status": "配布中",
    "product_type": "",
    "booking_period": "",
    "travel_period": "2025/11/13〜12/13 / (要エントリー・3万円以上)",
    "coupon_codes": [],
    "conditions": [
      "2025/11/13〜12/13 / (要エントリー・3万円以上)",
      "2025/11/13〜12/13 / (要エントリー・3万円以上)"
    ],
    "source_url": "https://camp.auone.jp/campaign/86306d646a2db26bf801c067",
    "detail_url": "https://camp.auone.jp/campaign/86306d646a2db26bf801c067",
    "source_type": "article_snapshot",
    "fetch_method": "existing_article_table",
    "last_checked": "2026-05-20",
    "confidence": "medium",
    "display_type": "table",
    "placement_hint": "",
    "detail_data": {
      "source": "/Users/takamacmini/projects/vault_box/vault_blog/旅クーポン/wp_articles/567_relux-discount-campaigns.json",
      "headers": [
        "キャンペーン/クーポン名",
        "割引/特典内容",
        "期間/条件"
      ]
    }
  },
  {
    "id": "relux-680891c5f4",
    "provider": "relux",
    "provider_label": "Relux",
    "site_targets": [
      "welltrip"
    ],
    "article_slug": "",
    "title": "→Pontaパス新規入会クーポン / ※auユーザー以外も入会可能",
    "category": "567_relux-discount-campaigns",
    "discount": "5,000円OFFクーポン",
    "stock_status": "配布中",
    "product_type": "",
    "booking_period": "",
    "travel_period": "常時開催 (要確認)",
    "coupon_codes": [],
    "conditions": [
      "常時開催 (要確認)",
      "常時開催 (要確認)"
    ],
    "source_url": "//ck.jp.ap.valuecommerce.com/servlet/referral?sid=3731913&pid=890987923&vc_url=https%3A%2F%2Frlx.jp%2Flp%2Fpontapass-coupon%2F",
    "detail_url": "//ck.jp.ap.valuecommerce.com/servlet/referral?sid=3731913&pid=890987923&vc_url=https%3A%2F%2Frlx.jp%2Flp%2Fpontapass-coupon%2F",
    "source_type": "article_snapshot",
    "fetch_method": "existing_article_table",
    "last_checked": "2026-05-20",
    "confidence": "medium",
    "display_type": "table",
    "placement_hint": "",
    "detail_data": {
      "source": "/Users/takamacmini/projects/vault_box/vault_blog/旅クーポン/wp_articles/567_relux-discount-campaigns.json",
      "headers": [
        "キャンペーン/クーポン名",
        "割引/特典内容",
        "期間/条件"
      ]
    }
  },
  {
    "id": "relux-cc3f0018d2",
    "provider": "relux",
    "provider_label": "Relux",
    "site_targets": [
      "welltrip"
    ],
    "article_slug": "",
    "title": "→ポイントアップキャンペーン",
    "category": "567_relux-discount-campaigns",
    "discount": "最大47％還元",
    "stock_status": "配布中",
    "product_type": "",
    "booking_period": "",
    "travel_period": "2025/12/26〜12/7",
    "coupon_codes": [],
    "conditions": [
      "2025/12/26〜12/7",
      "2025/12/26〜12/7"
    ],
    "source_url": "//ck.jp.ap.valuecommerce.com/servlet/referral?sid=3731913&pid=890987923&vc_url=https%3A%2F%2Frlx.jp%2Fpointup%2F",
    "detail_url": "//ck.jp.ap.valuecommerce.com/servlet/referral?sid=3731913&pid=890987923&vc_url=https%3A%2F%2Frlx.jp%2Fpointup%2F",
    "source_type": "article_snapshot",
    "fetch_method": "existing_article_table",
    "last_checked": "2026-05-20",
    "confidence": "medium",
    "display_type": "table",
    "placement_hint": "",
    "detail_data": {
      "source": "/Users/takamacmini/projects/vault_box/vault_blog/旅クーポン/wp_articles/567_relux-discount-campaigns.json",
      "headers": [
        "キャンペーン/クーポン名",
        "割引/特典内容",
        "期間/条件"
      ]
    }
  },
  {
    "id": "relux-df830231e8",
    "provider": "relux",
    "provider_label": "Relux",
    "site_targets": [
      "welltrip"
    ],
    "article_slug": "",
    "title": "→Winterポイントアップキャンペーン",
    "category": "567_relux-discount-campaigns",
    "discount": "ポイント即利用で / 5％OFF",
    "stock_status": "配布中",
    "product_type": "",
    "booking_period": "",
    "travel_period": "2025/11/10〜2026/1/6",
    "coupon_codes": [],
    "conditions": [
      "2025/11/10〜2026/1/6",
      "2025/11/10〜2026/1/6"
    ],
    "source_url": "//ck.jp.ap.valuecommerce.com/servlet/referral?sid=3731913&pid=890987923&vc_url=https%3A%2F%2Frlx.jp%2Fpointsokuriyou%2F",
    "detail_url": "//ck.jp.ap.valuecommerce.com/servlet/referral?sid=3731913&pid=890987923&vc_url=https%3A%2F%2Frlx.jp%2Fpointsokuriyou%2F",
    "source_type": "article_snapshot",
    "fetch_method": "existing_article_table",
    "last_checked": "2026-05-20",
    "confidence": "medium",
    "display_type": "table",
    "placement_hint": "",
    "detail_data": {
      "source": "/Users/takamacmini/projects/vault_box/vault_blog/旅クーポン/wp_articles/567_relux-discount-campaigns.json",
      "headers": [
        "キャンペーン/クーポン名",
        "割引/特典内容",
        "期間/条件"
      ]
    }
  },
  {
    "id": "relux-70dec38e84",
    "provider": "relux",
    "provider_label": "Relux",
    "site_targets": [
      "welltrip"
    ],
    "article_slug": "",
    "title": "→Relux新規会員限定5％クーポン",
    "category": "567_relux-discount-campaigns",
    "discount": "5%OFFクーポン",
    "stock_status": "配布中",
    "product_type": "",
    "booking_period": "",
    "travel_period": "常時開催 (期限注意)",
    "coupon_codes": [],
    "conditions": [
      "常時開催 (期限注意)",
      "常時開催 (期限注意)"
    ],
    "source_url": "//ck.jp.ap.valuecommerce.com/servlet/referral?sid=3731913&pid=890987923&vc_url=https%3A%2F%2Frlx.jp%2Fau_register%2F",
    "detail_url": "//ck.jp.ap.valuecommerce.com/servlet/referral?sid=3731913&pid=890987923&vc_url=https%3A%2F%2Frlx.jp%2Fau_register%2F",
    "source_type": "article_snapshot",
    "fetch_method": "existing_article_table",
    "last_checked": "2026-05-20",
    "confidence": "medium",
    "display_type": "table",
    "placement_hint": "",
    "detail_data": {
      "source": "/Users/takamacmini/projects/vault_box/vault_blog/旅クーポン/wp_articles/567_relux-discount-campaigns.json",
      "headers": [
        "キャンペーン/クーポン名",
        "割引/特典内容",
        "期間/条件"
      ]
    }
  },
  {
    "id": "relux-2a241649c7",
    "provider": "relux",
    "provider_label": "Relux",
    "site_targets": [
      "welltrip"
    ],
    "article_slug": "",
    "title": "→Relux会員限定特典価格",
    "category": "567_relux-discount-campaigns",
    "discount": "不明",
    "stock_status": "配布中",
    "product_type": "",
    "booking_period": "",
    "travel_period": "常時開催 (期限注意)",
    "coupon_codes": [],
    "conditions": [
      "常時開催 (期限注意)",
      "常時開催 (期限注意)"
    ],
    "source_url": "//ck.jp.ap.valuecommerce.com/servlet/referral?sid=3731913&pid=890987923&vc_url=https%3A%2F%2Frlx.jp%2Fsecret%2F",
    "detail_url": "//ck.jp.ap.valuecommerce.com/servlet/referral?sid=3731913&pid=890987923&vc_url=https%3A%2F%2Frlx.jp%2Fsecret%2F",
    "source_type": "article_snapshot",
    "fetch_method": "existing_article_table",
    "last_checked": "2026-05-20",
    "confidence": "medium",
    "display_type": "table",
    "placement_hint": "",
    "detail_data": {
      "source": "/Users/takamacmini/projects/vault_box/vault_blog/旅クーポン/wp_articles/567_relux-discount-campaigns.json",
      "headers": [
        "キャンペーン/クーポン名",
        "割引/特典内容",
        "期間/条件"
      ]
    }
  },
  {
    "id": "relux-3e0e99df3c",
    "provider": "relux",
    "provider_label": "Relux",
    "site_targets": [
      "welltrip"
    ],
    "article_slug": "",
    "title": "→三太郎の日クーポン",
    "category": "567_relux-discount-campaigns",
    "discount": "最大30%OFFクーポン / (抽選)",
    "stock_status": "配布中",
    "product_type": "",
    "booking_period": "",
    "travel_period": "毎月3, 13, 23日",
    "coupon_codes": [],
    "conditions": [
      "毎月3, 13, 23日",
      "毎月3, 13, 23日"
    ],
    "source_url": "//ck.jp.ap.valuecommerce.com/servlet/referral?sid=3731913&pid=890987923&vc_url=https%3A%2F%2Frlx.jp%2Flp%2Fpontapass%2F",
    "detail_url": "//ck.jp.ap.valuecommerce.com/servlet/referral?sid=3731913&pid=890987923&vc_url=https%3A%2F%2Frlx.jp%2Flp%2Fpontapass%2F",
    "source_type": "article_snapshot",
    "fetch_method": "existing_article_table",
    "last_checked": "2026-05-20",
    "confidence": "medium",
    "display_type": "table",
    "placement_hint": "",
    "detail_data": {
      "source": "/Users/takamacmini/projects/vault_box/vault_blog/旅クーポン/wp_articles/567_relux-discount-campaigns.json",
      "headers": [
        "キャンペーン/クーポン名",
        "割引/特典内容",
        "期間/条件"
      ]
    }
  }
]
