[
  {
    "ota": "JTB",
    "coupon_id": "2607yamanashi",
    "title": "山梨へGo！夏旅応援クーポン",
    "type": "🆕 新規",
    "tweet": "【JTB】新クーポン配布開始\n「山梨へGo！夏旅応援クーポン」\n割引: 最大10,000円引\nエリア: 山梨県\n詳細→ https://www.jtb.co.jp/myjtb/campaign/coupon/detail/2607yamanashi/page.asp\n#JTB #クーポン #旅行"
  },
  {
    "ota": "JTB",
    "coupon_id": "2607yng",
    "title": "【U-29旅応援！】　海外ツアールックJTBMySTYLEどこでも使えるクーポン＜9月-12月出発＞（10代）",
    "type": "🆕 新規",
    "tweet": "【JTB】新クーポン配布開始\n「【U-29旅応援！】　海外ツアールックJTBMySTYLEどこでも使えるクーポン＜9月-12月出発＞（10代）」\n割引: 最大28,000円引\nエリア: 全方面\n詳細→ https://www.jtb.co.jp/myjtb/campaign/kaigaicoupon/detail/2607yng/page.asp\n#JTB #クーポン #旅行"
  },
  {
    "ota": "JTB",
    "coupon_id": "2607yng2",
    "title": "【U-29旅応援！】　海外ツアールックJTBMySTYLEどこでも使えるクーポン＜9月-12月出発＞（20代）",
    "type": "🆕 新規",
    "tweet": "【JTB】新クーポン配布開始\n「【U-29旅応援！】　海外ツアールックJTBMySTYLEどこでも使えるクーポン＜9月-12月出発＞（20代）」\n割引: 最大28,000円引\nエリア: 全方面\n詳細→ https://www.jtb.co.jp/myjtb/campaign/kaigaicoupon/detail/2607yng2/page.asp\n#JTB #クーポン #旅行"
  },
  {
    "ota": "JTB",
    "coupon_id": "2607young",
    "title": "【U-29旅応援！】　国内ツアーで使える割引クーポン",
    "type": "🆕 新規",
    "tweet": "【JTB】新クーポン配布開始\n「【U-29旅応援！】　国内ツアーで使える割引クーポン」\n割引: 3,000円引\nエリア: 全国\n詳細→ https://www.jtb.co.jp/myjtb/campaign/coupon/detail/2607young/page.asp\n#JTB #クーポン #旅行"
  },
  {
    "ota": "JTB",
    "coupon_id": "2604nstoh",
    "title": "【7～9月宿泊】「日本の旬 東北」　東北エリアのおすすめ施設で使える割引クーポン",
    "type": "🟢 配布再開",
    "tweet": "【JTB】配布再開\n「【7～9月宿泊】「日本の旬 東北」　東北エリアのおすすめ施設で使える割引クーポン」\n割引: 最大10,000円引\nエリア: 青森県・岩手県・宮城県\n詳細→ https://www.jtb.co.jp/myjtb/campaign/coupon/detail/2604nstoh/page.asp\n#JTB #クーポン #旅行"
  },
  {
    "ota": "JTB",
    "coupon_id": "2606douto",
    "title": "<7～8月宿泊>【道東エリア】おすすめ施設で使える割引クーポン",
    "type": "🟢 配布再開",
    "tweet": "【JTB】配布再開\n「<7～8月宿泊>【道東エリア】おすすめ施設で使える割引クーポン」\n割引: 最大10,000円引\nエリア: 北海道\n詳細→ https://www.jtb.co.jp/myjtb/campaign/coupon/detail/2606douto/page.asp\n#JTB #クーポン #旅行"
  },
  {
    "ota": "JTB",
    "coupon_id": "2606hilton",
    "title": "全国のヒルトンおすすめ施設で使える割引クーポン",
    "type": "🟢 配布再開",
    "tweet": "【JTB】配布再開\n「全国のヒルトンおすすめ施設で使える割引クーポン」\n割引: 最大15,000円引\nエリア: 全国\n詳細→ https://www.jtb.co.jp/myjtb/campaign/coupon/detail/2606hilton/page.asp\n#JTB #クーポン #旅行"
  },
  {
    "ota": "JTB",
    "coupon_id": "2606okinawa",
    "title": "☆【沖縄】８月～９月出発☆お盆にも使える　おすすめ施設クーポン",
    "type": "🟢 配布再開",
    "tweet": "【JTB】配布再開\n「☆【沖縄】８月～９月出発☆お盆にも使える　おすすめ施設クーポン」\n割引: 最大20,000円引\nエリア: 沖縄県\n詳細→ https://www.jtb.co.jp/myjtb/campaign/coupon/detail/2606okinawa/page.asp\n#JTB #クーポン #旅行"
  }
]