[
  {
    "id": "tobu_top_tours-580bcbda20",
    "provider": "tobu_top_tours",
    "provider_label": "東武トップツアーズ",
    "site_targets": [
      "welltrip"
    ],
    "article_slug": "",
    "title": "→スゴ得",
    "category": "tobutoptours-coupon",
    "discount": "",
    "stock_status": "配布中",
    "product_type": "旅行代金（JR+宿泊）",
    "booking_period": "",
    "travel_period": "",
    "coupon_codes": [],
    "conditions": [],
    "source_url": "//ck.jp.ap.valuecommerce.com/servlet/referral?sid=3763413&pid=892569986&vc_url=https%3A%2F%2Ftobutoptours.jp%2Fsugotoku%2F",
    "detail_url": "//ck.jp.ap.valuecommerce.com/servlet/referral?sid=3763413&pid=892569986&vc_url=https%3A%2F%2Ftobutoptours.jp%2Fsugotoku%2F",
    "source_type": "article_snapshot",
    "fetch_method": "existing_article_table",
    "last_checked": "2026-05-20",
    "confidence": "medium",
    "display_type": "table",
    "placement_hint": "",
    "detail_data": {
      "source": "/Users/takamacmini/projects/vault_box/vault_blog/ウェルトリップ/会社別/東武トップツアーズ/note/tobutoptours-coupon.html",
      "headers": [
        "制度名",
        "割引対象",
        "割引の仕組み",
        "登録"
      ]
    }
  },
  {
    "id": "tobu_top_tours-cd578263d3",
    "provider": "tobu_top_tours",
    "provider_label": "東武トップツアーズ",
    "site_targets": [
      "welltrip"
    ],
    "article_slug": "",
    "title": "→ずらし旅",
    "category": "tobutoptours-coupon",
    "discount": "",
    "stock_status": "配布中",
    "product_type": "旅行代金＋体験",
    "booking_period": "",
    "travel_period": "",
    "coupon_codes": [],
    "conditions": [],
    "source_url": "//ck.jp.ap.valuecommerce.com/servlet/referral?sid=3763413&pid=892569986&vc_url=https%3A%2F%2Ftobutoptours.jp%2Fspecial%2Fzurashi_tabi%2F",
    "detail_url": "//ck.jp.ap.valuecommerce.com/servlet/referral?sid=3763413&pid=892569986&vc_url=https%3A%2F%2Ftobutoptours.jp%2Fspecial%2Fzurashi_tabi%2F",
    "source_type": "article_snapshot",
    "fetch_method": "existing_article_table",
    "last_checked": "2026-05-20",
    "confidence": "medium",
    "display_type": "table",
    "placement_hint": "",
    "detail_data": {
      "source": "/Users/takamacmini/projects/vault_box/vault_blog/ウェルトリップ/会社別/東武トップツアーズ/note/tobutoptours-coupon.html",
      "headers": [
        "制度名",
        "割引対象",
        "割引の仕組み",
        "登録"
      ]
    }
  },
  {
    "id": "tobu_top_tours-e299520760",
    "provider": "tobu_top_tours",
    "provider_label": "東武トップツアーズ",
    "site_targets": [
      "welltrip"
    ],
    "article_slug": "",
    "title": "→TOBU POINT",
    "category": "tobutoptours-coupon",
    "discount": "",
    "stock_status": "配布中",
    "product_type": "旅行代金（次回以降）※2026年秋よりWEB予約でも充当開始予定",
    "booking_period": "",
    "travel_period": "",
    "coupon_codes": [],
    "conditions": [],
    "source_url": "//ck.jp.ap.valuecommerce.com/servlet/referral?sid=3763413&pid=892569986&vc_url=https%3A%2F%2Fwww.tobupoint.jp%2F",
    "detail_url": "//ck.jp.ap.valuecommerce.com/servlet/referral?sid=3763413&pid=892569986&vc_url=https%3A%2F%2Fwww.tobupoint.jp%2F",
    "source_type": "article_snapshot",
    "fetch_method": "existing_article_table",
    "last_checked": "2026-05-20",
    "confidence": "medium",
    "display_type": "table",
    "placement_hint": "",
    "detail_data": {
      "source": "/Users/takamacmini/projects/vault_box/vault_blog/ウェルトリップ/会社別/東武トップツアーズ/note/tobutoptours-coupon.html",
      "headers": [
        "制度名",
        "割引対象",
        "割引の仕組み",
        "登録"
      ]
    }
  },
  {
    "id": "tobu_top_tours-c378d8785c",
    "provider": "tobu_top_tours",
    "provider_label": "東武トップツアーズ",
    "site_targets": [
      "welltrip"
    ],
    "article_slug": "",
    "title": "→トクトククーポン",
    "category": "tobutoptours-coupon",
    "discount": "",
    "stock_status": "配布中",
    "product_type": "現地施設（観光・飲食等）",
    "booking_period": "",
    "travel_period": "",
    "coupon_codes": [],
    "conditions": [],
    "source_url": "//ck.jp.ap.valuecommerce.com/servlet/referral?sid=3763413&pid=892569986&vc_url=https%3A%2F%2Ftokutoku-coupon.jp%2F",
    "detail_url": "//ck.jp.ap.valuecommerce.com/servlet/referral?sid=3763413&pid=892569986&vc_url=https%3A%2F%2Ftokutoku-coupon.jp%2F",
    "source_type": "article_snapshot",
    "fetch_method": "existing_article_table",
    "last_checked": "2026-05-20",
    "confidence": "medium",
    "display_type": "table",
    "placement_hint": "",
    "detail_data": {
      "source": "/Users/takamacmini/projects/vault_box/vault_blog/ウェルトリップ/会社別/東武トップツアーズ/note/tobutoptours-coupon.html",
      "headers": [
        "制度名",
        "割引対象",
        "割引の仕組み",
        "登録"
      ]
    }
  },
  {
    "id": "tobu_top_tours-1cf972a5af",
    "provider": "tobu_top_tours",
    "provider_label": "東武トップツアーズ",
    "site_targets": [
      "welltrip"
    ],
    "article_slug": "",
    "title": "→キャンペーンコード",
    "category": "tobutoptours-coupon",
    "discount": "",
    "stock_status": "配布中",
    "product_type": "—",
    "booking_period": "",
    "travel_period": "",
    "coupon_codes": [],
    "conditions": [],
    "source_url": "",
    "detail_url": "",
    "source_type": "article_snapshot",
    "fetch_method": "existing_article_table",
    "last_checked": "2026-05-20",
    "confidence": "medium",
    "display_type": "table",
    "placement_hint": "",
    "detail_data": {
      "source": "/Users/takamacmini/projects/vault_box/vault_blog/ウェルトリップ/会社別/東武トップツアーズ/note/tobutoptours-coupon.html",
      "headers": [
        "制度名",
        "割引対象",
        "割引の仕組み",
        "登録"
      ]
    }
  }
]
