{
  "last_updated": "2026-04-17T06:43:19.287426+09:00",
  "ids": {
    "f533c660d67a": {
      "category": "海外旅行",
      "title": "【夏先ドリキャンペーン】早めの予約がお得！最大60,000円引きクーポン",
      "discount": ""
    },
    "cd0b31366130": {
      "category": "海外ツアー",
      "title": "先着60名様限定！サンフランシスコ行きツアーお申込みでお1人様10,000円引きクーポン",
      "discount": ""
    },
    "7759e70177b0": {
      "category": "海外旅行",
      "title": "HISのクレジットカード「TAViCA」新規入会で5,000円引きクーポン",
      "discount": ""
    },
    "05ddc89733ef": {
      "category": "添乗員同行オーストラリアツアー",
      "title": "オンライン配信「旅情報LIVE」視聴者限定！添乗員同行オーストラリアツアーお1人様5,000円引き",
      "discount": ""
    },
    "c437f5cfd38d": {
      "category": "海外eSIM",
      "title": "期間中にTripSIMお申し込みで利用プラン10％OFF",
      "discount": "10%OFF"
    },
    "39bb2e583c4d": {
      "category": "国内旅行",
      "title": "【夏先ドリキャンペーン】早めの予約がお得！最大10,000円引きクーポン",
      "discount": ""
    },
    "a180fc8fc715": {
      "category": "国内ツアー",
      "title": "早めの予約がお得！120日以上前までのお申し込みでお1人様最大5,000円引きクーポン",
      "discount": ""
    },
    "843e980acff6": {
      "category": "国内ツアー・国内航空券＋ホテル",
      "title": "JALまたはJTA利用限定！初夏の空旅10,000円引きクーポン",
      "discount": ""
    },
    "b58b0e413159": {
      "category": "国内航空券＋ホテル",
      "title": "早めの予約がお得！90日以上前までのお申し込みで最大10,000円引きクーポン",
      "discount": ""
    },
    "89fb6709b716": {
      "category": "国内航空券＋ホテル",
      "title": "4～6月出発がお得！5,000円引きクーポン",
      "discount": ""
    },
    "ad10f634c1bb": {
      "category": "北海道ツアー",
      "title": "【北海道キャンペーン】60日以上前までのお申し込みで最大10％引きクーポン",
      "discount": ""
    },
    "5d1b069eaf79": {
      "category": "北海道行き航空券＋ホテル",
      "title": "【北海道キャンペーン】3～9月出発の北海道旅行がお得！最大8,000円引きクーポン",
      "discount": ""
    },
    "f210c731de66": {
      "category": "北海道行き添乗員同行ツアー",
      "title": "【北海道キャンペーン】60日以上前までのお申し込みでお1人様最大10,000円引きクーポン",
      "discount": ""
    },
    "5f58ff8394a4": {
      "category": "四国ツアー",
      "title": "【四国キャンペーン】60日以上前までのお申し込みで最大10％引きクーポン",
      "discount": ""
    },
    "ead5278e500f": {
      "category": "四国行き航空券＋ホテル",
      "title": "【四国キャンペーン】レンタカーとセット予約がお得2,000円引きクーポン",
      "discount": ""
    },
    "72c9defeae32": {
      "category": "関東ツアー",
      "title": "【関東キャンペーン】早めの予約がお得！最大10％引きクーポン",
      "discount": ""
    },
    "4bd3477bdd41": {
      "category": "関東行き航空券＋ホテル",
      "title": "【関東キャンペーン】東京や横浜など関東行きの旅行がお得2,000円引きクーポン",
      "discount": ""
    },
    "4cf361fd757a": {
      "category": "沖縄ツアー",
      "title": "夏の沖縄家族旅行がお得！最大20％引きクーポン",
      "discount": ""
    },
    "4e1dc1f2e945": {
      "category": "沖縄ツアー",
      "title": "沖縄NEWオールインクルーシブプラン限定！最大10％引きクーポン",
      "discount": ""
    },
    "d7d2d6539bd0": {
      "category": "国内添乗員同行ツアー",
      "title": "早めの予約がお得！90日以上前までのお申し込みでお1人様最大10,000円引きクーポン",
      "discount": ""
    },
    "d1e595b033de": {
      "category": "国内バスツアー",
      "title": "早めの予約がお得！60日以上前までのお申し込みでお1人様最大3,000円引きクーポン",
      "discount": ""
    },
    "ddc9ea32581c": {
      "category": "国内ホテル",
      "title": "早めの予約がお得！30日以上前までのお申し込みで最大4,000円引きクーポン",
      "discount": ""
    },
    "b538fa5530c2": {
      "category": "国内ホテル",
      "title": "3・4月の宿泊がお得！3,000円引きクーポン",
      "discount": ""
    },
    "06e2b04398cc": {
      "category": "国内航空券",
      "title": "スカイマーク、PeachまたはJetstarの往復航空券がお得！取扱手数料半額クーポン",
      "discount": ""
    },
    "1eae2b875c77": {
      "category": "高速バス・夜行バス",
      "title": "WILLER EXPRESS利用で最大10％引きクーポン",
      "discount": ""
    },
    "be4fa34aae01": {
      "category": "高速バス・夜行バス",
      "title": "新生活応援！25歳以下ならお得！お1人様5％引きクーポン",
      "discount": ""
    },
    "7b7c5c287f69": {
      "category": "変なホテル",
      "title": "夏休みも連休もお得！変なホテル公式サイトで使える10％引きクーポン",
      "discount": ""
    },
    "96281cd79d35": {
      "category": "満天ノ 辻のや",
      "title": "夏休みも連休もお得！満天ノ 辻のや公式サイトで使える10％引きクーポン",
      "discount": ""
    }
  }
}